{
  "Producers": [
    {
      "addr": "cardano-relay.cryptoaware.io",
      "port": 6000,
      "valency": 1
    },
    {
      "addr": "cardano-relay1.cryptoaware.io",
      "port": 6000,
      "valency": 1
    },
    {
      "addr": "95.217.120.208",
      "port": 3001,
      "valency": 1
    },
    {
      "addr": "116.202.131.185",
      "port": 3002,
      "valency": 1
    },
    {
      "addr": "relay1.masp-pool.nl",
      "port": 3001,
      "valency": 1
    },
    {
      "addr": "relay2.masp-pool.nl",
      "port": 3001,
      "valency": 1
    },
    {
      "addr": "adapool.crazycareergames.com",
      "port": 4001,
      "valency": 1
    },
    {
      "addr": "adapool.crazycareergames.com",
      "port": 4002,
      "valency": 1
    },
    {
      "addr": "86.87.250.133",
      "port": 3001,
      "valency": 1
    },
    {
      "addr": "45.74.216.198",
      "port": 3001,
      "valency": 1
    },
    {
      "addr": "45.74.216.198",
      "port": 3002,
      "valency": 1
    },
    {
      "addr": "164.90.154.253",
      "port": 6000,
      "valency": 1
    },
    {
      "addr": "104.131.34.79",
      "port": 6000,
      "valency": 1
    },
    {
      "addr": "relays-new.cardano-mainnet.iohk.io",
      "port": 3001,
      "valency": 2
    }
  ]
}
